jupyter_app_launcher/__init__.py
jupyter_app_launcher/_version.py
jupyter_app_launcher/handler_factory_manager.py
jupyter_app_launcher/handlers.py
jupyter_app_launcher/script.py
jupyter_app_launcher/utils.py
jupyter_app_launcher/factories/__init__.py
jupyter_app_launcher/factories/base_factory.py
jupyter_app_launcher/factories/notebook_voila_factory.py
jupyter_app_launcher/factories/url_factory.py
jupyter_app_launcher/schema/config.schema.json
jupyter_app_launcher-0.3.1.data/data/etc/jupyter/jupyter_server_config.d/jupyter_app_launcher.json
jupyter_app_launcher-0.3.1.data/data/share/jupyter/labextensions/jupyter_app_launcher/package.json
jupyter_app_launcher-0.3.1.data/data/share/jupyter/labextensions/jupyter_app_launcher/static/24.064fdc839336b31a1912.js
jupyter_app_launcher-0.3.1.data/data/share/jupyter/labextensions/jupyter_app_launcher/static/526.2dda23b9254c1257f6f7.js
jupyter_app_launcher-0.3.1.data/data/share/jupyter/labextensions/jupyter_app_launcher/static/668.d1e2775e166b785467bd.js
jupyter_app_launcher-0.3.1.data/data/share/jupyter/labextensions/jupyter_app_launcher/static/668.d1e2775e166b785467bd.js.LICENSE.txt
jupyter_app_launcher-0.3.1.data/data/share/jupyter/labextensions/jupyter_app_launcher/static/remoteEntry.1403bfc94922a4ce703a.js
jupyter_app_launcher-0.3.1.data/data/share/jupyter/labextensions/jupyter_app_launcher/static/style.js
jupyter_app_launcher-0.3.1.data/data/share/jupyter/labextensions/jupyter_app_launcher/static/third-party-licenses.json
jupyter_app_launcher-0.3.1.data/data/share/jupyter/labextensions/jupyter_app_launcher/install.json
jupyter_app_launcher-0.3.1.dist-info/METADATA
jupyter_app_launcher-0.3.1.dist-info/WHEEL
jupyter_app_launcher-0.3.1.dist-info/entry_points.txt
jupyter_app_launcher-0.3.1.dist-info/licenses/LICENSE
jupyter_app_launcher-0.3.1.dist-info/RECORD
