Metadata-Version: 2.3
Name: jupyter_app_launcher
Version: 0.3.1
Dynamic: Keywords
Summary: A JupyterLab extension.
Project-URL: Homepage, https://github.com/trungleduc/jupyter_app_launcher
Project-URL: Bug Tracker, https://github.com/trungleduc/jupyter_app_launcher/issues
Project-URL: Repository, https://github.com/trungleduc/jupyter_app_launcher.git
Author-email: Trung Le <leductrungxf@gmail.com>
License: BSD 3-Clause License
License-File: LICENSE
Classifier: Framework :: Jupyter
Classifier: Framework :: Jupyter :: JupyterLab
Classifier: Framework :: Jupyter :: JupyterLab :: 4
Classifier: Framework :: Jupyter :: JupyterLab :: Extensions
Classifier: Framework :: Jupyter :: JupyterLab :: Extensions :: Prebuilt
Classifier: License :: OSI Approved :: BSD License
Classifier: Programming Language :: Python
Classifier: Programming Language :: Python :: 3
Classifier: Programming Language :: Python :: 3.8
Classifier: Programming Language :: Python :: 3.9
Classifier: Programming Language :: Python :: 3.10
Classifier: Programming Language :: Python :: 3.11
Classifier: Programming Language :: Python :: 3.12
Requires-Python: >=3.8
Requires-Dist: jsonschema
Requires-Dist: jupyter-server-proxy<5,>=4.1.0
Requires-Dist: jupyter-server<3,>=2.0.1
Requires-Dist: pyyaml
